{"characterId":"9775f3af-9db7-4d2d-83fe-f12c9120b2dd","name":"Schmathias","radius":32.0,"moveVelocity":600.0,"abilities":[{"name":"Frog Punch","abilityId":"c4745e52-aae8-4651-910e-8372693ed26c","type":"MELEE","radius":64.0,"distanceFromChar":48.0,"speed":0.0,"activeTime":5,"startupTime":3,"executionTime":5,"endlagTime":3,"rechargeTime":20,"damage":150.0,"baseKnockback":700.0,"knockbackRatio":0.8,"knockbackPoint":-48.0,"knockbackTowardPoint":false},{"name":"Hook","abilityId":"8ddff0a1-36f5-43df-a6d5-431a2436e2a6","type":"PROJECTILE","radius":24.0,"distanceFromChar":32.0,"speed":900.0,"activeTime":30,"startupTime":5,"executionTime":0,"endlagTime":18,"rechargeTime":50,"damage":200.0,"baseKnockback":1400.0,"knockbackRatio":0.2,"knockbackPoint":-128.0,"knockbackTowardPoint":true},{"name":"Meteor Punch","abilityId":"faf219cc-3e8f-40dd-853a-bc720fdaa5d3","type":"MELEE","radius":32.0,"distanceFromChar":64.0,"speed":0.0,"activeTime":3,"startupTime":15,"executionTime":3,"endlagTime":4,"rechargeTime":60,"damage":500.0,"baseKnockback":1000.0,"knockbackRatio":1.5,"knockbackPoint":-128.0,"knockbackTowardPoint":false}]}
